maskfill/__init__.py
maskfill/maskfill.py
tests/__init__.py
tests/test_maskfill.py
maskfill-1.1.1.dist-info/LICENSE
maskfill-1.1.1.dist-info/METADATA
maskfill-1.1.1.dist-info/WHEEL
maskfill-1.1.1.dist-info/entry_points.txt
maskfill-1.1.1.dist-info/top_level.txt
maskfill-1.1.1.dist-info/RECORD
