Metadata-Version: 2.1
Name: maskfill
Version: 1.1.1
Summary: A Python package for image mask filling
Home-page: https://github.com/dokkum/maskfill
Download-URL: https://github.com/dokkum/maskfill/archive/refs/tags/v1.1.1.tar.gz
Author: Pieter van Dokkum & Imad Pasha
Author-email: Pieter van Dokkum <pieter.vandokkum@yale.edu>, Imad Pasha <imad.pasha@yale.edu>
License: MIT License
Classifier: Development Status :: 4 - Beta
Classifier: Intended Audience :: Science/Research
Classifier: License :: OSI Approved :: MIT License
Classifier: Programming Language :: Python :: 3
Classifier: Programming Language :: Python :: 3.7
Classifier: Programming Language :: Python :: 3.8
Classifier: Programming Language :: Python :: 3.9
Classifier: Programming Language :: Python :: 3.10
Requires-Python: >=3.6
License-File: LICENSE
Requires-Dist: numpy
Requires-Dist: astropy
Requires-Dist: scipy
Provides-Extra: testing
Requires-Dist: pytest ; extra == 'testing'
